clipscope/__init__.py
clipscope/hookedvit.py
clipscope/sae.py
clipscope-0.1.8.dist-info/METADATA
clipscope-0.1.8.dist-info/WHEEL
clipscope-0.1.8.dist-info/RECORD
