Metadata-Version: 2.1
Name: clipscope
Version: 0.1.8
Summary: 
Author: Louka Ewington-Pitsos
Author-email: lewingtonpitsos@gmail.com
Requires-Python: >=3.9,<4.0
Classifier: Programming Language :: Python :: 3
Classifier: Programming Language :: Python :: 3.9
Classifier: Programming Language :: Python :: 3.10
Classifier: Programming Language :: Python :: 3.11
Classifier: Programming Language :: Python :: 3.12
Requires-Dist: huggingface-hub (>=0.25.2,<0.26.0)
Requires-Dist: torch (>=2.5.0,<3.0.0)
Requires-Dist: transformers (>=4.45.2,<5.0.0)
